caplot/__init__.py
caplot/interactiveplot.py
caplot/manhattan.py
caplot/pca.py
caplot/refgen.yaml
caplot-0.1.1.dist-info/LICENSE
caplot-0.1.1.dist-info/METADATA
caplot-0.1.1.dist-info/WHEEL
caplot-0.1.1.dist-info/top_level.txt
caplot-0.1.1.dist-info/zip-safe
caplot-0.1.1.dist-info/RECORD
