Metadata-Version: 2.1
Name: caplot
Version: 0.1.1
Summary: Cohort Analysis Plot
Home-page: UNKNOWN
Author: Arash Bayat
Author-email: a.bayat@garvan.org.au
License: MIT
Keywords: visualization,cohort analysis
Platform: UNKNOWN
Classifier: Development Status :: 4 - Beta
Classifier: Intended Audience :: Education
Classifier: Intended Audience :: Science/Research
Classifier: License :: OSI Approved :: MIT License
Classifier: Programming Language :: Python
Classifier: Programming Language :: Python :: 3
Classifier: Programming Language :: Python :: 3.9
Classifier: Topic :: Scientific/Engineering :: Visualization
Requires-Dist: bokeh
Requires-Dist: ipywidgets
Requires-Dist: munch
Requires-Dist: pandas
Requires-Dist: pandasql
Requires-Dist: pyyaml
Requires-Dist: requests
Requires-Dist: selenium
Requires-Dist: stringcase
Requires-Dist: svglib
Requires-Dist: chromedriver-binary
